literature_knowledgebase/__init__.py
literature_knowledgebase/admin.py
literature_knowledgebase/apps.py
literature_knowledgebase/choices.py
literature_knowledgebase/filters.py
literature_knowledgebase/managers.py
literature_knowledgebase/models.py
literature_knowledgebase/serializers.py
literature_knowledgebase/services.py
literature_knowledgebase/urls.py
literature_knowledgebase/utils.py
literature_knowledgebase/views.py
literature_knowledgebase/viewsets.py
literature_knowledgebase/migrations/0001_initial.py
literature_knowledgebase/migrations/0002_article_file.py
literature_knowledgebase/migrations/__init__.py
django_literature_knowledgebase-0.7.8.dist-info/AUTHORS.rst
django_literature_knowledgebase-0.7.8.dist-info/LICENSE
django_literature_knowledgebase-0.7.8.dist-info/METADATA
django_literature_knowledgebase-0.7.8.dist-info/WHEEL
django_literature_knowledgebase-0.7.8.dist-info/top_level.txt
django_literature_knowledgebase-0.7.8.dist-info/RECORD
