Metadata-Version: 2.1
Name: django-literature-knowledgebase
Version: 0.7.8
Summary: Django app for creating a knowledge base of curated literature
Home-page: https://github.com/genomics-geek/django-literature-knowledgebase
Author: Michael A. Gonzalez
Author-email: GonzalezMA@email.chop.edu
License: MIT
Keywords: django-literature-knowledgebase
Platform: UNKNOWN
Classifier: Development Status :: 4 - Beta
Classifier: Framework :: Django :: 2.0
Classifier: Framework :: Django :: 2.1
Classifier: Framework :: Django :: 2.2
Classifier: Intended Audience :: Developers
Classifier: License :: OSI Approved :: BSD License
Classifier: Natural Language :: English
Classifier: Programming Language :: Python :: 3
Classifier: Programming Language :: Python :: 3.5
Classifier: Programming Language :: Python :: 3.6
Requires-Dist: djangorestframework (==3.10.3)
Requires-Dist: django-filter (==2.2.0)
Requires-Dist: django-genomix (==0.6.10)
Requires-Dist: django-model-utils (==3.2.0)
Requires-Dist: django-user-activities (==0.5.11)
Requires-Dist: xmltodict (==0.12.0)
